dns_manager-1.0.0.dist-info/METADATA
dns_manager-1.0.0.dist-info/WHEEL
dns_manager-1.0.0.dist-info/entry_points.txt
dns_manager-1.0.0.dist-info/licenses/LICENSE
dns_manager/__init__.py
dns_manager/__main__.py
dns_manager/__version__.py
dns_manager/getter/__init__.py
dns_manager/getter/base.py
dns_manager/getter/public.py
dns_manager/getter/snmp.py
dns_manager/getter/utils.py
dns_manager/model/__init__.py
dns_manager/model/config.py
dns_manager/model/record.py
dns_manager/setter/__init__.py
dns_manager/setter/base.py
dns_manager/setter/lexicon.py
dns_manager/utils.py
dns_manager-1.0.0.dist-info/RECORD
