Metadata-Version: 2.1
Name: dns-manager
Version: 1.0.0
Summary: Manage your DNS records with ease.
Author-Email: Zhan Rongrui <2742392377@qq.com>
License: GNU GENERAL PUBLIC LICENSE
Classifier: Environment :: Console
Classifier: License :: OSI Approved :: GNU General Public License v3 (GPLv3)
Classifier: Operating System :: OS Independent
Classifier: Programming Language :: Python
Classifier: Programming Language :: Python :: 3
Classifier: Programming Language :: Python :: 3.10
Classifier: Programming Language :: Python :: 3.11
Classifier: Programming Language :: Python :: 3.12
Classifier: Programming Language :: Python :: 3.13
Classifier: Programming Language :: Python :: Implementation :: CPython
Classifier: Typing :: Typed
Project-URL: Homepage, https://github.com/zrr1999/dns-manager.git
Project-URL: Repository, https://github.com/zrr1999/dns-manager.git
Requires-Python: >=3.10
Requires-Dist: cachetools>=5.3.2
Requires-Dist: dns-lexicon>=3.17.0
Requires-Dist: httpx>=0.26.0
Requires-Dist: loguru>=0.7.2
Requires-Dist: pydantic>=2.5.3
Requires-Dist: pyparsing>=3.1.1
Requires-Dist: pyyaml>=6.0.1
Requires-Dist: rich>=13.7.0
Requires-Dist: rtoml>=0.12.0
Requires-Dist: scapy>=2.5.0
Requires-Dist: typer>=0.15.2
Provides-Extra: all
Requires-Dist: dns-manager[watch]; extra == "all"
Provides-Extra: dev
Requires-Dist: pyright; extra == "dev"
Requires-Dist: ruff; extra == "dev"
Requires-Dist: xdoctest; extra == "dev"
Requires-Dist: pytest; extra == "dev"
Requires-Dist: pytest-cov; extra == "dev"
Requires-Dist: pytest-codspeed; extra == "dev"
Requires-Dist: pytest-asyncio; extra == "dev"
Provides-Extra: watch
Requires-Dist: watchfiles; extra == "watch"
